natnetsdk/DataDescriptions.py
natnetsdk/MoCapData.py
natnetsdk/NatNetClient.py
natnetsdk/__init__.py
natnetsdk/__main__.py
natnetsdk-4.1.1.dist-info/METADATA
natnetsdk-4.1.1.dist-info/WHEEL
natnetsdk-4.1.1.dist-info/RECORD
