Metadata-Version: 2.1
Name: natnetsdk
Version: 4.1.1
Summary: Python's natnetsdk now on PyPI!!!
Home-page: https://optitrack.com/
License: Apache-2.0
Author: optitrack
Requires-Python: ==3.*
Classifier: License :: OSI Approved :: Apache Software License
Classifier: Programming Language :: Python :: 3
Classifier: Programming Language :: Python :: 3.4
Classifier: Programming Language :: Python :: 3.5
Classifier: Programming Language :: Python :: 3.6
Classifier: Programming Language :: Python :: 3.7
Classifier: Programming Language :: Python :: 3.8
Classifier: Programming Language :: Python :: 3.9
Classifier: Programming Language :: Python :: 3.10
Classifier: Programming Language :: Python :: 3.11
Classifier: Programming Language :: Python :: 3.12
Project-URL: latest releases, https://optitrack.com/support/downloads/developer-tools.html
